ltb_s/__init__.py
Letter2Binary-1.0.dist-info/METADATA
Letter2Binary-1.0.dist-info/WHEEL
Letter2Binary-1.0.dist-info/top_level.txt
Letter2Binary-1.0.dist-info/RECORD
